ingi/__init__.py
ingi/cache.py
ingi/run.py
ingi_cli-0.1.1.dist-info/LICENSE
ingi_cli-0.1.1.dist-info/METADATA
ingi_cli-0.1.1.dist-info/WHEEL
ingi_cli-0.1.1.dist-info/entry_points.txt
ingi_cli-0.1.1.dist-info/top_level.txt
ingi_cli-0.1.1.dist-info/RECORD
