Metadata-Version: 2.1
Name: ingi-cli
Version: 0.1.1
Summary: A CLI tool for gists like no other. Run, download and help build a searchable gist API
Home-page: UNKNOWN
Author: Ian Loubser
Author-email: loubser.ian@gmail.com
License: UNKNOWN
Platform: UNKNOWN
Requires-Dist: pickleDB (==0.9.2)
Requires-Dist: coverage (==4.5.3)
Requires-Dist: pytest-cov (==2.6.1)
Requires-Dist: python-coveralls (==2.9.1)
Requires-Dist: python-dateutil (==2.8.0)
Requires-Dist: requests (==2.21.0)
Requires-Dist: requests-mock (==1.5.2)
